{"nodes": [{"id": "backend_ai_logger_py", "label": "logger.py", "file_type": "code", "source_file": "backend/ai/logger.py", "source_location": "L1"}, {"id": "logger_aicallrecord", "label": "AICallRecord", "file_type": "code", "source_file": "backend/ai/logger.py", "source_location": "L13"}, {"id": "logger_aicalllogger", "label": "AICallLogger", "file_type": "code", "source_file": "backend/ai/logger.py", "source_location": "L28"}, {"id": "logger_aicalllogger_init", "label": ".__init__()", "file_type": "code", "source_file": "backend/ai/logger.py", "source_location": "L41"}, {"id": "logger_aicalllogger_estimate_cost", "label": ".estimate_cost()", "file_type": "code", "source_file": "backend/ai/logger.py", "source_location": "L47"}, {"id": "logger_aicalllogger_log_call", "label": ".log_call()", "file_type": "code", "source_file": "backend/ai/logger.py", "source_location": "L56"}, {"id": "logger_aicalllogger_write_to_file", "label": "._write_to_file()", "file_type": "code", "source_file": "backend/ai/logger.py", "source_location": "L99"}, {"id": "logger_aicalllogger_log_to_database", "label": ".log_to_database()", "file_type": "code", "source_file": "backend/ai/logger.py", "source_location": "L106"}, {"id": "logger_aicalllogger_get_daily_stats", "label": ".get_daily_stats()", "file_type": "code", "source_file": "backend/ai/logger.py", "source_location": "L129"}, {"id": "logger_get_ai_logger", "label": "get_ai_logger()", "file_type": "code", "source_file": "backend/ai/logger.py", "source_location": "L182"}, {"id": "logger_rationale_1", "label": "AI call logging for monitoring and debugging.", "file_type": "rationale", "source_file": "backend/ai/logger.py", "source_location": "L1"}, {"id": "logger_rationale_29", "label": "Log AI API calls to file, database, and console.", "file_type": "rationale", "source_file": "backend/ai/logger.py", "source_location": "L29"}], "edges": [{"source": "backend_ai_logger_py", "target": "json", "relation": "imports", "confidence": "EXTRACTED", "source_file": "backend/ai/logger.py", "source_location": "L2", "weight": 1.0}, {"source": "backend_ai_logger_py", "target": "logging", "relation": "imports", "confidence": "EXTRACTED", "source_file": "backend/ai/logger.py", "source_location": "L3", "weight": 1.0}, {"source": "backend_ai_logger_py", "target": "datetime", "relation": "imports_from", "confidence": "EXTRACTED", "source_file": "backend/ai/logger.py", "source_location": "L4", "weight": 1.0}, {"source": "backend_ai_logger_py", "target": "pathlib", "relation": "imports_from", "confidence": "EXTRACTED", "source_file": "backend/ai/logger.py", "source_location": "L5", "weight": 1.0}, {"source": "backend_ai_logger_py", "target": "typing", "relation": "imports_from", "confidence": "EXTRACTED", "source_file": "backend/ai/logger.py", "source_location": "L6", "weight": 1.0}, {"source": "backend_ai_logger_py", "target": "dataclasses", "relation": "imports_from", "confidence": "EXTRACTED", "source_file": "backend/ai/logger.py", "source_location": "L7", "weight": 1.0}, {"source": "backend_ai_logger_py", "target": "logger_aicallrecord", "relation": "contains", "confidence": "EXTRACTED", "source_file": "backend/ai/logger.py", "source_location": "L13", "weight": 1.0}, {"source": "backend_ai_logger_py", "target": "logger_aicalllogger", "relation": "contains", "confidence": "EXTRACTED", "source_file": "backend/ai/logger.py", "source_location": "L28", "weight": 1.0}, {"source": "logger_aicalllogger", "target": "logger_aicalllogger_init", "relation": "method", "confidence": "EXTRACTED", "source_file": "backend/ai/logger.py", "source_location": "L41", "weight": 1.0}, {"source": "logger_aicalllogger", "target": "logger_aicalllogger_estimate_cost", "relation": "method", "confidence": "EXTRACTED", "source_file": "backend/ai/logger.py", "source_location": "L47", "weight": 1.0}, {"source": "logger_aicalllogger", "target": "logger_aicalllogger_log_call", "relation": "method", "confidence": "EXTRACTED", "source_file": "backend/ai/logger.py", "source_location": "L56", "weight": 1.0}, {"source": "logger_aicalllogger", "target": "logger_aicalllogger_write_to_file", "relation": "method", "confidence": "EXTRACTED", "source_file": "backend/ai/logger.py", "source_location": "L99", "weight": 1.0}, {"source": "logger_aicalllogger", "target": "logger_aicalllogger_log_to_database", "relation": "method", "confidence": "EXTRACTED", "source_file": "backend/ai/logger.py", "source_location": "L106", "weight": 1.0}, {"source": "logger_aicalllogger", "target": "logger_aicalllogger_get_daily_stats", "relation": "method", "confidence": "EXTRACTED", "source_file": "backend/ai/logger.py", "source_location": "L129", "weight": 1.0}, {"source": "backend_ai_logger_py", "target": "logger_get_ai_logger", "relation": "contains", "confidence": "EXTRACTED", "source_file": "backend/ai/logger.py", "source_location": "L182", "weight": 1.0}, {"source": "logger_aicalllogger_log_call", "target": "logger_aicalllogger_estimate_cost", "relation": "calls", "confidence": "EXTRACTED", "source_file": "backend/ai/logger.py", "source_location": "L69", "weight": 1.0}, {"source": "logger_aicalllogger_log_call", "target": "logger_aicallrecord", "relation": "calls", "confidence": "EXTRACTED", "source_file": "backend/ai/logger.py", "source_location": "L71", "weight": 1.0}, {"source": "logger_aicalllogger_log_call", "target": "logger_aicalllogger_write_to_file", "relation": "calls", "confidence": "EXTRACTED", "source_file": "backend/ai/logger.py", "source_location": "L86", "weight": 1.0}, {"source": "logger_get_ai_logger", "target": "logger_aicalllogger", "relation": "calls", "confidence": "EXTRACTED", "source_file": "backend/ai/logger.py", "source_location": "L185", "weight": 1.0}, {"source": "logger_rationale_1", "target": "backend_ai_logger_py", "relation": "rationale_for", "confidence": "EXTRACTED", "source_file": "backend/ai/logger.py", "source_location": "L1", "weight": 1.0}, {"source": "logger_rationale_29", "target": "logger_aicalllogger", "relation": "rationale_for", "confidence": "EXTRACTED", "source_file": "backend/ai/logger.py", "source_location": "L29", "weight": 1.0}], "raw_calls": [{"caller_nid": "logger_aicalllogger_init", "callee": "Path", "source_file": "backend/ai/logger.py", "source_location": "L42"}, {"caller_nid": "logger_aicalllogger_init", "callee": "mkdir", "source_file": "backend/ai/logger.py", "source_location": "L43"}, {"caller_nid": "logger_aicalllogger_init", "callee": "strftime", "source_file": "backend/ai/logger.py", "source_location": "L45"}, {"caller_nid": "logger_aicalllogger_init", "callee": "now", "source_file": "backend/ai/logger.py", "source_location": "L45"}, {"caller_nid": "logger_aicalllogger_log_call", "callee": "isoformat", "source_file": "backend/ai/logger.py", "source_location": "L72"}, {"caller_nid": "logger_aicalllogger_log_call", "callee": "now", "source_file": "backend/ai/logger.py", "source_location": "L72"}, {"caller_nid": "logger_aicalllogger_log_call", "callee": "debug", "source_file": "backend/ai/logger.py", "source_location": "L93"}, {"caller_nid": "logger_aicalllogger_log_call", "callee": "warning", "source_file": "backend/ai/logger.py", "source_location": "L95"}, {"caller_nid": "logger_aicalllogger_write_to_file", "callee": "open", "source_file": "backend/ai/logger.py", "source_location": "L101"}, {"caller_nid": "logger_aicalllogger_write_to_file", "callee": "write", "source_file": "backend/ai/logger.py", "source_location": "L102"}, {"caller_nid": "logger_aicalllogger_write_to_file", "callee": "dumps", "source_file": "backend/ai/logger.py", "source_location": "L102"}, {"caller_nid": "logger_aicalllogger_write_to_file", "callee": "asdict", "source_file": "backend/ai/logger.py", "source_location": "L102"}, {"caller_nid": "logger_aicalllogger_write_to_file", "callee": "error", "source_file": "backend/ai/logger.py", "source_location": "L104"}, {"caller_nid": "logger_aicalllogger_log_to_database", "callee": "AILog", "source_file": "backend/ai/logger.py", "source_location": "L113"}, {"caller_nid": "logger_aicalllogger_log_to_database", "callee": "fromisoformat", "source_file": "backend/ai/logger.py", "source_location": "L114"}, {"caller_nid": "logger_aicalllogger_log_to_database", "callee": "add", "source_file": "backend/ai/logger.py", "source_location": "L124"}, {"caller_nid": "logger_aicalllogger_log_to_database", "callee": "commit", "source_file": "backend/ai/logger.py", "source_location": "L125"}, {"caller_nid": "logger_aicalllogger_log_to_database", "callee": "error", "source_file": "backend/ai/logger.py", "source_location": "L127"}, {"caller_nid": "logger_aicalllogger_get_daily_stats", "callee": "exists", "source_file": "backend/ai/logger.py", "source_location": "L141"}, {"caller_nid": "logger_aicalllogger_get_daily_stats", "callee": "open", "source_file": "backend/ai/logger.py", "source_location": "L145"}, {"caller_nid": "logger_aicalllogger_get_daily_stats", "callee": "loads", "source_file": "backend/ai/logger.py", "source_location": "L148"}, {"caller_nid": "logger_aicalllogger_get_daily_stats", "callee": "get", "source_file": "backend/ai/logger.py", "source_location": "L150"}, {"caller_nid": "logger_aicalllogger_get_daily_stats", "callee": "get", "source_file": "backend/ai/logger.py", "source_location": "L151"}, {"caller_nid": "logger_aicalllogger_get_daily_stats", "callee": "append", "source_file": "backend/ai/logger.py", "source_location": "L152"}, {"caller_nid": "logger_aicalllogger_get_daily_stats", "callee": "get", "source_file": "backend/ai/logger.py", "source_location": "L152"}, {"caller_nid": "logger_aicalllogger_get_daily_stats", "callee": "get", "source_file": "backend/ai/logger.py", "source_location": "L154"}, {"caller_nid": "logger_aicalllogger_get_daily_stats", "callee": "get", "source_file": "backend/ai/logger.py", "source_location": "L157"}, {"caller_nid": "logger_aicalllogger_get_daily_stats", "callee": "get", "source_file": "backend/ai/logger.py", "source_location": "L162"}, {"caller_nid": "logger_aicalllogger_get_daily_stats", "callee": "sum", "source_file": "backend/ai/logger.py", "source_location": "L171"}, {"caller_nid": "logger_aicalllogger_get_daily_stats", "callee": "len", "source_file": "backend/ai/logger.py", "source_location": "L171"}, {"caller_nid": "logger_aicalllogger_get_daily_stats", "callee": "error", "source_file": "backend/ai/logger.py", "source_location": "L174"}]}