{"nodes": [{"id": "backend_job_queue_arq_settings_py", "label": "arq_settings.py", "file_type": "code", "source_file": "backend/job_queue/arq_settings.py", "source_location": "L1"}, {"id": "arq_settings_market_scan", "label": "market_scan()", "file_type": "code", "source_file": "backend/job_queue/arq_settings.py", "source_location": "L15"}, {"id": "arq_settings_settlement_check", "label": "settlement_check()", "file_type": "code", "source_file": "backend/job_queue/arq_settings.py", "source_location": "L20"}, {"id": "arq_settings_signal_generation", "label": "signal_generation()", "file_type": "code", "source_file": "backend/job_queue/arq_settings.py", "source_location": "L25"}, {"id": "arq_settings_workersettings", "label": "WorkerSettings", "file_type": "code", "source_file": "backend/job_queue/arq_settings.py", "source_location": "L30"}, {"id": "arq_settings_rationale_1", "label": "arq Worker configuration for PolyEdge job queue.  Start the worker with:     arq", "file_type": "rationale", "source_file": "backend/job_queue/arq_settings.py", "source_location": "L1"}, {"id": "arq_settings_rationale_16", "label": "arq task wrapper for market_scan handler.", "file_type": "rationale", "source_file": "backend/job_queue/arq_settings.py", "source_location": "L16"}, {"id": "arq_settings_rationale_21", "label": "arq task wrapper for settlement_check handler.", "file_type": "rationale", "source_file": "backend/job_queue/arq_settings.py", "source_location": "L21"}, {"id": "arq_settings_rationale_26", "label": "arq task wrapper for signal_generation handler.", "file_type": "rationale", "source_file": "backend/job_queue/arq_settings.py", "source_location": "L26"}, {"id": "arq_settings_rationale_31", "label": "arq Worker configuration.", "file_type": "rationale", "source_file": "backend/job_queue/arq_settings.py", "source_location": "L31"}], "edges": [{"source": "backend_job_queue_arq_settings_py", "target": "arq_connections", "relation": "imports_from", "confidence": "EXTRACTED", "source_file": "backend/job_queue/arq_settings.py", "source_location": "L9", "weight": 1.0}, {"source": "backend_job_queue_arq_settings_py", "target": "backend_config", "relation": "imports_from", "confidence": "EXTRACTED", "source_file": "backend/job_queue/arq_settings.py", "source_location": "L11", "weight": 1.0}, {"source": "backend_job_queue_arq_settings_py", "target": "backend_job_queue", "relation": "imports_from", "confidence": "EXTRACTED", "source_file": "backend/job_queue/arq_settings.py", "source_location": "L12", "weight": 1.0}, {"source": "backend_job_queue_arq_settings_py", "target": "arq_settings_market_scan", "relation": "contains", "confidence": "EXTRACTED", "source_file": "backend/job_queue/arq_settings.py", "source_location": "L15", "weight": 1.0}, {"source": "backend_job_queue_arq_settings_py", "target": "arq_settings_settlement_check", "relation": "contains", "confidence": "EXTRACTED", "source_file": "backend/job_queue/arq_settings.py", "source_location": "L20", "weight": 1.0}, {"source": "backend_job_queue_arq_settings_py", "target": "arq_settings_signal_generation", "relation": "contains", "confidence": "EXTRACTED", "source_file": "backend/job_queue/arq_settings.py", "source_location": "L25", "weight": 1.0}, {"source": "backend_job_queue_arq_settings_py", "target": "arq_settings_workersettings", "relation": "contains", "confidence": "EXTRACTED", "source_file": "backend/job_queue/arq_settings.py", "source_location": "L30", "weight": 1.0}, {"source": "arq_settings_rationale_1", "target": "backend_job_queue_arq_settings_py", "relation": "rationale_for", "confidence": "EXTRACTED", "source_file": "backend/job_queue/arq_settings.py", "source_location": "L1", "weight": 1.0}, {"source": "arq_settings_rationale_16", "target": "arq_settings_market_scan", "relation": "rationale_for", "confidence": "EXTRACTED", "source_file": "backend/job_queue/arq_settings.py", "source_location": "L16", "weight": 1.0}, {"source": "arq_settings_rationale_21", "target": "arq_settings_settlement_check", "relation": "rationale_for", "confidence": "EXTRACTED", "source_file": "backend/job_queue/arq_settings.py", "source_location": "L21", "weight": 1.0}, {"source": "arq_settings_rationale_26", "target": "arq_settings_signal_generation", "relation": "rationale_for", "confidence": "EXTRACTED", "source_file": "backend/job_queue/arq_settings.py", "source_location": "L26", "weight": 1.0}, {"source": "arq_settings_rationale_31", "target": "arq_settings_workersettings", "relation": "rationale_for", "confidence": "EXTRACTED", "source_file": "backend/job_queue/arq_settings.py", "source_location": "L31", "weight": 1.0}], "raw_calls": []}