{"nodes": [{"id": "backend_core_agi_jobs_py", "label": "agi_jobs.py", "file_type": "code", "source_file": "backend/core/agi_jobs.py", "source_location": "L1"}, {"id": "agi_jobs_self_review_job", "label": "self_review_job()", "file_type": "code", "source_file": "backend/core/agi_jobs.py", "source_location": "L8"}, {"id": "agi_jobs_research_pipeline_job", "label": "research_pipeline_job()", "file_type": "code", "source_file": "backend/core/agi_jobs.py", "source_location": "L30"}, {"id": "agi_jobs_rationale_1", "label": "Scheduled job wrappers for AGI-loop components (self-review, research).", "file_type": "rationale", "source_file": "backend/core/agi_jobs.py", "source_location": "L1"}, {"id": "agi_jobs_rationale_9", "label": "Run the self-review cycle: attribution, postmortems, degradation detection.", "file_type": "rationale", "source_file": "backend/core/agi_jobs.py", "source_location": "L9"}, {"id": "agi_jobs_rationale_31", "label": "Run the autonomous research pipeline: RSS, BigBrain search, scoring.", "file_type": "rationale", "source_file": "backend/core/agi_jobs.py", "source_location": "L31"}], "edges": [{"source": "backend_core_agi_jobs_py", "target": "logging", "relation": "imports", "confidence": "EXTRACTED", "source_file": "backend/core/agi_jobs.py", "source_location": "L3", "weight": 1.0}, {"source": "backend_core_agi_jobs_py", "target": "agi_jobs_self_review_job", "relation": "contains", "confidence": "EXTRACTED", "source_file": "backend/core/agi_jobs.py", "source_location": "L8", "weight": 1.0}, {"source": "backend_core_agi_jobs_py", "target": "agi_jobs_research_pipeline_job", "relation": "contains", "confidence": "EXTRACTED", "source_file": "backend/core/agi_jobs.py", "source_location": "L30", "weight": 1.0}, {"source": "agi_jobs_rationale_1", "target": "backend_core_agi_jobs_py", "relation": "rationale_for", "confidence": "EXTRACTED", "source_file": "backend/core/agi_jobs.py", "source_location": "L1", "weight": 1.0}, {"source": "agi_jobs_rationale_9", "target": "agi_jobs_self_review_job", "relation": "rationale_for", "confidence": "EXTRACTED", "source_file": "backend/core/agi_jobs.py", "source_location": "L9", "weight": 1.0}, {"source": "agi_jobs_rationale_31", "target": "agi_jobs_research_pipeline_job", "relation": "rationale_for", "confidence": "EXTRACTED", "source_file": "backend/core/agi_jobs.py", "source_location": "L31", "weight": 1.0}], "raw_calls": [{"caller_nid": "agi_jobs_self_review_job", "callee": "log_event", "source_file": "backend/core/agi_jobs.py", "source_location": "L12"}, {"caller_nid": "agi_jobs_self_review_job", "callee": "SelfReview", "source_file": "backend/core/agi_jobs.py", "source_location": "L16"}, {"caller_nid": "agi_jobs_self_review_job", "callee": "run_review_cycle", "source_file": "backend/core/agi_jobs.py", "source_location": "L17"}, {"caller_nid": "agi_jobs_self_review_job", "callee": "len", "source_file": "backend/core/agi_jobs.py", "source_location": "L19"}, {"caller_nid": "agi_jobs_self_review_job", "callee": "get", "source_file": "backend/core/agi_jobs.py", "source_location": "L19"}, {"caller_nid": "agi_jobs_self_review_job", "callee": "len", "source_file": "backend/core/agi_jobs.py", "source_location": "L20"}, {"caller_nid": "agi_jobs_self_review_job", "callee": "get", "source_file": "backend/core/agi_jobs.py", "source_location": "L20"}, {"caller_nid": "agi_jobs_self_review_job", "callee": "log_event", "source_file": "backend/core/agi_jobs.py", "source_location": "L21"}, {"caller_nid": "agi_jobs_self_review_job", "callee": "exception", "source_file": "backend/core/agi_jobs.py", "source_location": "L26"}, {"caller_nid": "agi_jobs_self_review_job", "callee": "log_event", "source_file": "backend/core/agi_jobs.py", "source_location": "L27"}, {"caller_nid": "agi_jobs_research_pipeline_job", "callee": "log_event", "source_file": "backend/core/agi_jobs.py", "source_location": "L34"}, {"caller_nid": "agi_jobs_research_pipeline_job", "callee": "ResearchPipeline", "source_file": "backend/core/agi_jobs.py", "source_location": "L38"}, {"caller_nid": "agi_jobs_research_pipeline_job", "callee": "run_research_cycle", "source_file": "backend/core/agi_jobs.py", "source_location": "L39"}, {"caller_nid": "agi_jobs_research_pipeline_job", "callee": "log_event", "source_file": "backend/core/agi_jobs.py", "source_location": "L41"}, {"caller_nid": "agi_jobs_research_pipeline_job", "callee": "len", "source_file": "backend/core/agi_jobs.py", "source_location": "L43"}, {"caller_nid": "agi_jobs_research_pipeline_job", "callee": "exception", "source_file": "backend/core/agi_jobs.py", "source_location": "L46"}, {"caller_nid": "agi_jobs_research_pipeline_job", "callee": "log_event", "source_file": "backend/core/agi_jobs.py", "source_location": "L47"}]}