{"nodes": [{"id": "tests_test_validation_api_py", "label": "test_validation_api.py", "file_type": "code", "source_file": "tests/test_validation_api.py", "source_location": "L1"}, {"id": "test_validation_api_testsignalvalidationapi", "label": "TestSignalValidationAPI", "file_type": "code", "source_file": "tests/test_validation_api.py", "source_location": "L10"}, {"id": "test_validation_api_testsignalvalidationapi_test_invalid_signal_returns_422", "label": ".test_invalid_signal_returns_422()", "file_type": "code", "source_file": "tests/test_validation_api.py", "source_location": "L13"}, {"id": "test_validation_api_testsignalvalidationapi_test_missing_required_field_returns_422", "label": ".test_missing_required_field_returns_422()", "file_type": "code", "source_file": "tests/test_validation_api.py", "source_location": "L29"}, {"id": "test_validation_api_testsignalvalidationapi_test_html_injection_sanitized", "label": ".test_html_injection_sanitized()", "file_type": "code", "source_file": "tests/test_validation_api.py", "source_location": "L44"}, {"id": "test_validation_api_testwalletvalidationapi", "label": "TestWalletValidationAPI", "file_type": "code", "source_file": "tests/test_validation_api.py", "source_location": "L61"}, {"id": "test_validation_api_testwalletvalidationapi_test_invalid_wallet_address_returns_422", "label": ".test_invalid_wallet_address_returns_422()", "file_type": "code", "source_file": "tests/test_validation_api.py", "source_location": "L64"}, {"id": "test_validation_api_testwalletvalidationapi_test_too_many_tags_returns_422", "label": ".test_too_many_tags_returns_422()", "file_type": "code", "source_file": "tests/test_validation_api.py", "source_location": "L79"}, {"id": "test_validation_api_teststrategyvalidationapi", "label": "TestStrategyValidationAPI", "file_type": "code", "source_file": "tests/test_validation_api.py", "source_location": "L93"}, {"id": "test_validation_api_teststrategyvalidationapi_test_invalid_interval_returns_422", "label": ".test_invalid_interval_returns_422()", "file_type": "code", "source_file": "tests/test_validation_api.py", "source_location": "L96"}, {"id": "test_validation_api_testbacktestvalidationapi", "label": "TestBacktestValidationAPI", "file_type": "code", "source_file": "tests/test_validation_api.py", "source_location": "L112"}, {"id": "test_validation_api_testbacktestvalidationapi_test_invalid_kelly_fraction_returns_422", "label": ".test_invalid_kelly_fraction_returns_422()", "file_type": "code", "source_file": "tests/test_validation_api.py", "source_location": "L115"}, {"id": "test_validation_api_testproposalvalidationapi", "label": "TestProposalValidationAPI", "file_type": "code", "source_file": "tests/test_validation_api.py", "source_location": "L131"}, {"id": "test_validation_api_testproposalvalidationapi_test_empty_change_details_returns_422", "label": ".test_empty_change_details_returns_422()", "file_type": "code", "source_file": "tests/test_validation_api.py", "source_location": "L134"}, {"id": "test_validation_api_testproposalvalidationapi_test_impact_out_of_range_returns_422", "label": ".test_impact_out_of_range_returns_422()", "file_type": "code", "source_file": "tests/test_validation_api.py", "source_location": "L147"}, {"id": "test_validation_api_testvalidationerrormessages", "label": "TestValidationErrorMessages", "file_type": "code", "source_file": "tests/test_validation_api.py", "source_location": "L159"}, {"id": "test_validation_api_testvalidationerrormessages_test_error_message_includes_field_location", "label": ".test_error_message_includes_field_location()", "file_type": "code", "source_file": "tests/test_validation_api.py", "source_location": "L162"}, {"id": "test_validation_api_testvalidationerrormessages_test_multiple_validation_errors_returned", "label": ".test_multiple_validation_errors_returned()", "file_type": "code", "source_file": "tests/test_validation_api.py", "source_location": "L181"}, {"id": "test_validation_api_rationale_1", "label": "Integration tests for API validation error responses.", "file_type": "rationale", "source_file": "tests/test_validation_api.py", "source_location": "L1"}, {"id": "test_validation_api_rationale_11", "label": "Test signal creation API validation.", "file_type": "rationale", "source_file": "tests/test_validation_api.py", "source_location": "L11"}, {"id": "test_validation_api_rationale_62", "label": "Test wallet API validation.", "file_type": "rationale", "source_file": "tests/test_validation_api.py", "source_location": "L62"}, {"id": "test_validation_api_rationale_94", "label": "Test strategy configuration API validation.", "file_type": "rationale", "source_file": "tests/test_validation_api.py", "source_location": "L94"}, {"id": "test_validation_api_rationale_113", "label": "Test backtest API validation.", "file_type": "rationale", "source_file": "tests/test_validation_api.py", "source_location": "L113"}, {"id": "test_validation_api_rationale_132", "label": "Test proposal API validation.", "file_type": "rationale", "source_file": "tests/test_validation_api.py", "source_location": "L132"}, {"id": "test_validation_api_rationale_160", "label": "Test that validation errors have clear, actionable messages.", "file_type": "rationale", "source_file": "tests/test_validation_api.py", "source_location": "L160"}], "edges": [{"source": "tests_test_validation_api_py", "target": "pytest", "relation": "imports", "confidence": "EXTRACTED", "source_file": "tests/test_validation_api.py", "source_location": "L3", "weight": 1.0}, {"source": "tests_test_validation_api_py", "target": "fastapi_testclient", "relation": "imports_from", "confidence": "EXTRACTED", "source_file": "tests/test_validation_api.py", "source_location": "L4", "weight": 1.0}, {"source": "tests_test_validation_api_py", "target": "backend_api_main", "relation": "imports_from", "confidence": "EXTRACTED", "source_file": "tests/test_validation_api.py", "source_location": "L5", "weight": 1.0}, {"source": "tests_test_validation_api_py", "target": "test_validation_api_testsignalvalidationapi", "relation": "contains", "confidence": "EXTRACTED", "source_file": "tests/test_validation_api.py", "source_location": "L10", "weight": 1.0}, {"source": "test_validation_api_testsignalvalidationapi", "target": "test_validation_api_testsignalvalidationapi_test_invalid_signal_returns_422", "relation": "method", "confidence": "EXTRACTED", "source_file": "tests/test_validation_api.py", "source_location": "L13", "weight": 1.0}, {"source": "test_validation_api_testsignalvalidationapi", "target": "test_validation_api_testsignalvalidationapi_test_missing_required_field_returns_422", "relation": "method", "confidence": "EXTRACTED", "source_file": "tests/test_validation_api.py", "source_location": "L29", "weight": 1.0}, {"source": "test_validation_api_testsignalvalidationapi", "target": "test_validation_api_testsignalvalidationapi_test_html_injection_sanitized", "relation": "method", "confidence": "EXTRACTED", "source_file": "tests/test_validation_api.py", "source_location": "L44", "weight": 1.0}, {"source": "tests_test_validation_api_py", "target": "test_validation_api_testwalletvalidationapi", "relation": "contains", "confidence": "EXTRACTED", "source_file": "tests/test_validation_api.py", "source_location": "L61", "weight": 1.0}, {"source": "test_validation_api_testwalletvalidationapi", "target": "test_validation_api_testwalletvalidationapi_test_invalid_wallet_address_returns_422", "relation": "method", "confidence": "EXTRACTED", "source_file": "tests/test_validation_api.py", "source_location": "L64", "weight": 1.0}, {"source": "test_validation_api_testwalletvalidationapi", "target": "test_validation_api_testwalletvalidationapi_test_too_many_tags_returns_422", "relation": "method", "confidence": "EXTRACTED", "source_file": "tests/test_validation_api.py", "source_location": "L79", "weight": 1.0}, {"source": "tests_test_validation_api_py", "target": "test_validation_api_teststrategyvalidationapi", "relation": "contains", "confidence": "EXTRACTED", "source_file": "tests/test_validation_api.py", "source_location": "L93", "weight": 1.0}, {"source": "test_validation_api_teststrategyvalidationapi", "target": "test_validation_api_teststrategyvalidationapi_test_invalid_interval_returns_422", "relation": "method", "confidence": "EXTRACTED", "source_file": "tests/test_validation_api.py", "source_location": "L96", "weight": 1.0}, {"source": "tests_test_validation_api_py", "target": "test_validation_api_testbacktestvalidationapi", "relation": "contains", "confidence": "EXTRACTED", "source_file": "tests/test_validation_api.py", "source_location": "L112", "weight": 1.0}, {"source": "test_validation_api_testbacktestvalidationapi", "target": "test_validation_api_testbacktestvalidationapi_test_invalid_kelly_fraction_returns_422", "relation": "method", "confidence": "EXTRACTED", "source_file": "tests/test_validation_api.py", "source_location": "L115", "weight": 1.0}, {"source": "tests_test_validation_api_py", "target": "test_validation_api_testproposalvalidationapi", "relation": "contains", "confidence": "EXTRACTED", "source_file": "tests/test_validation_api.py", "source_location": "L131", "weight": 1.0}, {"source": "test_validation_api_testproposalvalidationapi", "target": "test_validation_api_testproposalvalidationapi_test_empty_change_details_returns_422", "relation": "method", "confidence": "EXTRACTED", "source_file": "tests/test_validation_api.py", "source_location": "L134", "weight": 1.0}, {"source": "test_validation_api_testproposalvalidationapi", "target": "test_validation_api_testproposalvalidationapi_test_impact_out_of_range_returns_422", "relation": "method", "confidence": "EXTRACTED", "source_file": "tests/test_validation_api.py", "source_location": "L147", "weight": 1.0}, {"source": "tests_test_validation_api_py", "target": "test_validation_api_testvalidationerrormessages", "relation": "contains", "confidence": "EXTRACTED", "source_file": "tests/test_validation_api.py", "source_location": "L159", "weight": 1.0}, {"source": "test_validation_api_testvalidationerrormessages", "target": "test_validation_api_testvalidationerrormessages_test_error_message_includes_field_location", "relation": "method", "confidence": "EXTRACTED", "source_file": "tests/test_validation_api.py", "source_location": "L162", "weight": 1.0}, {"source": "test_validation_api_testvalidationerrormessages", "target": "test_validation_api_testvalidationerrormessages_test_multiple_validation_errors_returned", "relation": "method", "confidence": "EXTRACTED", "source_file": "tests/test_validation_api.py", "source_location": "L181", "weight": 1.0}, {"source": "test_validation_api_rationale_1", "target": "tests_test_validation_api_py", "relation": "rationale_for", "confidence": "EXTRACTED", "source_file": "tests/test_validation_api.py", "source_location": "L1", "weight": 1.0}, {"source": "test_validation_api_rationale_11", "target": "test_validation_api_testsignalvalidationapi", "relation": "rationale_for", "confidence": "EXTRACTED", "source_file": "tests/test_validation_api.py", "source_location": "L11", "weight": 1.0}, {"source": "test_validation_api_rationale_62", "target": "test_validation_api_testwalletvalidationapi", "relation": "rationale_for", "confidence": "EXTRACTED", "source_file": "tests/test_validation_api.py", "source_location": "L62", "weight": 1.0}, {"source": "test_validation_api_rationale_94", "target": "test_validation_api_teststrategyvalidationapi", "relation": "rationale_for", "confidence": "EXTRACTED", "source_file": "tests/test_validation_api.py", "source_location": "L94", "weight": 1.0}, {"source": "test_validation_api_rationale_113", "target": "test_validation_api_testbacktestvalidationapi", "relation": "rationale_for", "confidence": "EXTRACTED", "source_file": "tests/test_validation_api.py", "source_location": "L113", "weight": 1.0}, {"source": "test_validation_api_rationale_132", "target": "test_validation_api_testproposalvalidationapi", "relation": "rationale_for", "confidence": "EXTRACTED", "source_file": "tests/test_validation_api.py", "source_location": "L132", "weight": 1.0}, {"source": "test_validation_api_rationale_160", "target": "test_validation_api_testvalidationerrormessages", "relation": "rationale_for", "confidence": "EXTRACTED", "source_file": "tests/test_validation_api.py", "source_location": "L160", "weight": 1.0}], "raw_calls": [{"caller_nid": "test_validation_api_testsignalvalidationapi_test_invalid_signal_returns_422", "callee": "post", "source_file": "tests/test_validation_api.py", "source_location": "L14"}, {"caller_nid": "test_validation_api_testsignalvalidationapi_test_invalid_signal_returns_422", "callee": "json", "source_file": "tests/test_validation_api.py", "source_location": "L25"}, {"caller_nid": "test_validation_api_testsignalvalidationapi_test_invalid_signal_returns_422", "callee": "any", "source_file": "tests/test_validation_api.py", "source_location": "L27"}, {"caller_nid": "test_validation_api_testsignalvalidationapi_test_invalid_signal_returns_422", "callee": "lower", "source_file": "tests/test_validation_api.py", "source_location": "L27"}, {"caller_nid": "test_validation_api_testsignalvalidationapi_test_invalid_signal_returns_422", "callee": "str", "source_file": "tests/test_validation_api.py", "source_location": "L27"}, {"caller_nid": "test_validation_api_testsignalvalidationapi_test_missing_required_field_returns_422", "callee": "post", "source_file": "tests/test_validation_api.py", "source_location": "L30"}, {"caller_nid": "test_validation_api_testsignalvalidationapi_test_missing_required_field_returns_422", "callee": "json", "source_file": "tests/test_validation_api.py", "source_location": "L40"}, {"caller_nid": "test_validation_api_testsignalvalidationapi_test_missing_required_field_returns_422", "callee": "any", "source_file": "tests/test_validation_api.py", "source_location": "L42"}, {"caller_nid": "test_validation_api_testsignalvalidationapi_test_missing_required_field_returns_422", "callee": "lower", "source_file": "tests/test_validation_api.py", "source_location": "L42"}, {"caller_nid": "test_validation_api_testsignalvalidationapi_test_missing_required_field_returns_422", "callee": "str", "source_file": "tests/test_validation_api.py", "source_location": "L42"}, {"caller_nid": "test_validation_api_testsignalvalidationapi_test_html_injection_sanitized", "callee": "post", "source_file": "tests/test_validation_api.py", "source_location": "L45"}, {"caller_nid": "test_validation_api_testsignalvalidationapi_test_html_injection_sanitized", "callee": "json", "source_file": "tests/test_validation_api.py", "source_location": "L56"}, {"caller_nid": "test_validation_api_testsignalvalidationapi_test_html_injection_sanitized", "callee": "get", "source_file": "tests/test_validation_api.py", "source_location": "L57"}, {"caller_nid": "test_validation_api_testsignalvalidationapi_test_html_injection_sanitized", "callee": "get", "source_file": "tests/test_validation_api.py", "source_location": "L58"}, {"caller_nid": "test_validation_api_testwalletvalidationapi_test_invalid_wallet_address_returns_422", "callee": "setattr", "source_file": "tests/test_validation_api.py", "source_location": "L65"}, {"caller_nid": "test_validation_api_testwalletvalidationapi_test_invalid_wallet_address_returns_422", "callee": "post", "source_file": "tests/test_validation_api.py", "source_location": "L67"}, {"caller_nid": "test_validation_api_testwalletvalidationapi_test_invalid_wallet_address_returns_422", "callee": "json", "source_file": "tests/test_validation_api.py", "source_location": "L76"}, {"caller_nid": "test_validation_api_testwalletvalidationapi_test_too_many_tags_returns_422", "callee": "setattr", "source_file": "tests/test_validation_api.py", "source_location": "L80"}, {"caller_nid": "test_validation_api_testwalletvalidationapi_test_too_many_tags_returns_422", "callee": "post", "source_file": "tests/test_validation_api.py", "source_location": "L82"}, {"caller_nid": "test_validation_api_testwalletvalidationapi_test_too_many_tags_returns_422", "callee": "range", "source_file": "tests/test_validation_api.py", "source_location": "L86"}, {"caller_nid": "test_validation_api_teststrategyvalidationapi_test_invalid_interval_returns_422", "callee": "setattr", "source_file": "tests/test_validation_api.py", "source_location": "L97"}, {"caller_nid": "test_validation_api_teststrategyvalidationapi_test_invalid_interval_returns_422", "callee": "put", "source_file": "tests/test_validation_api.py", "source_location": "L99"}, {"caller_nid": "test_validation_api_teststrategyvalidationapi_test_invalid_interval_returns_422", "callee": "json", "source_file": "tests/test_validation_api.py", "source_location": "L107"}, {"caller_nid": "test_validation_api_teststrategyvalidationapi_test_invalid_interval_returns_422", "callee": "any", "source_file": "tests/test_validation_api.py", "source_location": "L109"}, {"caller_nid": "test_validation_api_teststrategyvalidationapi_test_invalid_interval_returns_422", "callee": "lower", "source_file": "tests/test_validation_api.py", "source_location": "L109"}, {"caller_nid": "test_validation_api_teststrategyvalidationapi_test_invalid_interval_returns_422", "callee": "str", "source_file": "tests/test_validation_api.py", "source_location": "L109"}, {"caller_nid": "test_validation_api_testbacktestvalidationapi_test_invalid_kelly_fraction_returns_422", "callee": "setattr", "source_file": "tests/test_validation_api.py", "source_location": "L116"}, {"caller_nid": "test_validation_api_testbacktestvalidationapi_test_invalid_kelly_fraction_returns_422", "callee": "post", "source_file": "tests/test_validation_api.py", "source_location": "L118"}, {"caller_nid": "test_validation_api_testbacktestvalidationapi_test_invalid_kelly_fraction_returns_422", "callee": "json", "source_file": "tests/test_validation_api.py", "source_location": "L127"}, {"caller_nid": "test_validation_api_testproposalvalidationapi_test_empty_change_details_returns_422", "callee": "post", "source_file": "tests/test_validation_api.py", "source_location": "L135"}, {"caller_nid": "test_validation_api_testproposalvalidationapi_test_empty_change_details_returns_422", "callee": "json", "source_file": "tests/test_validation_api.py", "source_location": "L144"}, {"caller_nid": "test_validation_api_testproposalvalidationapi_test_impact_out_of_range_returns_422", "callee": "post", "source_file": "tests/test_validation_api.py", "source_location": "L148"}, {"caller_nid": "test_validation_api_testvalidationerrormessages_test_error_message_includes_field_location", "callee": "post", "source_file": "tests/test_validation_api.py", "source_location": "L163"}, {"caller_nid": "test_validation_api_testvalidationerrormessages_test_error_message_includes_field_location", "callee": "json", "source_file": "tests/test_validation_api.py", "source_location": "L174"}, {"caller_nid": "test_validation_api_testvalidationerrormessages_test_multiple_validation_errors_returned", "callee": "post", "source_file": "tests/test_validation_api.py", "source_location": "L182"}, {"caller_nid": "test_validation_api_testvalidationerrormessages_test_multiple_validation_errors_returned", "callee": "json", "source_file": "tests/test_validation_api.py", "source_location": "L193"}, {"caller_nid": "test_validation_api_testvalidationerrormessages_test_multiple_validation_errors_returned", "callee": "len", "source_file": "tests/test_validation_api.py", "source_location": "L194"}]}